mathWiz/__init__.py
mathWiz/complex.py
mathWiz/mathWiz.py
mathWiz/matrices.py
mathWiz/polynomial.py
mathWiz/simultaneous.py
mathWiz/vectors.py
mathWiz-0.2.2.dist-info/LICENSE
mathWiz-0.2.2.dist-info/METADATA
mathWiz-0.2.2.dist-info/WHEEL
mathWiz-0.2.2.dist-info/top_level.txt
mathWiz-0.2.2.dist-info/RECORD
