Metadata-Version: 2.1
Name: mathWiz
Version: 0.2.2
Summary: A python math module designed for complex math.
Home-page: https://github.com/William-deg/mathWiz
Author: William E.
Author-email: "William E." <williamemerick10@gmail.com>
License: MIT
Project-URL: Changelog, https://github.com/William-deg/mathWiz/blob/master/CHANGELOG.md
Classifier: Programming Language :: Python :: 3
Classifier: License :: OSI Approved :: MIT License
Classifier: Operating System :: OS Independent
License-File: LICENSE
